{
  "id": "fiori-showcase-app-worklist-ui5-deploy-yaml",
  "title": "ui5 deploy",
  "category": "fiori-features",
  "path": "app/worklist/ui5-deploy.yaml",
  "lastModified": "2025-09-29T10:06:39.213Z",
  "tags": [
    "fiori-features",
    "yaml",
    "ui5",
    "deploy"
  ],
  "headers": [],
  "content": "# ui5-deploy.yaml\n\n```yaml\n# yaml-language-server: $schema=https://sap.github.io/ui5-tooling/schema/ui5.yaml.json\nspecVersion: '3.1'\nmetadata:\n  name: worklist\ntype: application\nresources:\n  configuration:\n    propertiesFileSourceEncoding: UTF-8\nbuilder:\n  resources:\n    excludes:\n      - \"/test/**\"\n      - \"/localService/**\"\n  customTasks:\n    - name: ui5-task-zipper\n      afterTask: generateVersionInfo\n      configuration:\n        archiveName: worklist\n        relativePaths: true\n        additionalFiles:\n          - xs-app.json\n    - name: ui5-tooling-transpile-task\n      afterTask: replaceVersion\n\n```",
  "excerpt": "ui5-deploy.yaml",
  "wordCount": 44,
  "version": "1.0.0",
  "source": "fiori-showcase",
  "sourceType": "github"
}